zalgo/__init__.py
zalgo/__main__.py
zalgo/zalgo.py
zalgotext-0.2.0.dist-info/DESCRIPTION.rst
zalgotext-0.2.0.dist-info/entry_points.txt
zalgotext-0.2.0.dist-info/METADATA
zalgotext-0.2.0.dist-info/metadata.json
zalgotext-0.2.0.dist-info/RECORD
zalgotext-0.2.0.dist-info/top_level.txt
zalgotext-0.2.0.dist-info/WHEEL
